{
  "version": "5.10.1",
  "flags": {},
  "shapes": [
    {
      "label": "脑膜瘤",
      "points": [
        [
          262.25,
          210.91071428571428
        ],
        [
          235.4642857142857,
          210.01785714285714
        ],
        [
          219.39285714285714,
          226.08928571428572
        ],
        [
          216.71428571428575,
          241.26785714285714
        ],
        [
          219.39285714285714,
          255.55357142857142
        ],
        [
          236.35714285714286,
          260.91071428571433
        ],
        [
          256.8928571428571,
          260.91071428571433
        ],
        [
          276.53571428571433,
          251.08928571428572
        ],
        [
          284.57142857142856,
          247.51785714285714
        ],
        [
          282.78571428571433,
          229.66071428571428
        ],
        [
          277.42857142857144,
          219.83928571428572
        ]
      ],
      "group_id": null,
      "description": "",
      "shape_type": "polygon",
      "flags": {},
      "mask": null
    }
  ],
  "imagePath": "..\\48.png",
  "imageData": null,
  "imageHeight": 512,
  "imageWidth": 512
}